azcam_lbtguiders/__init__.py
azcam_lbtguiders/cli_commands.py
azcam_lbtguiders/console.py
azcam_lbtguiders/gcs.py
azcam_lbtguiders/index_lbtguiders.html
azcam_lbtguiders/lbtguiders_configuration.txt
azcam_lbtguiders/lbtguiders_configuration_DESKTOP-OMPL2IU.txt
azcam_lbtguiders/server.py
azcam_lbtguiders/start_azcamtool.py
azcam_lbtguiders/dspcode/dsppci/pci3.lod
azcam_lbtguiders/dspcode/dsppci/pci3.s
azcam_lbtguiders/dspcode/dsppci/pci3_host.bat
azcam_lbtguiders/dspcode/dsppci/pci3boot.asm
azcam_lbtguiders/dspcode/dsppci/pci3boot.ls
azcam_lbtguiders/dspcode/dsptiming/agw1g/dacs.asm
azcam_lbtguiders/dspcode/dsptiming/agw1g/int_noise.asm
azcam_lbtguiders/dspcode/dsptiming/agw1g/int_signal.asm
azcam_lbtguiders/dspcode/dsptiming/agw1g/p_3123_mpp.asm
azcam_lbtguiders/dspcode/dsptiming/agw1g/pq_3123_mpp.asm
azcam_lbtguiders/dspcode/dsptiming/agw1g/s_12_123n.asm
azcam_lbtguiders/dspcode/dsptiming/agw1g/switchstates.asm
azcam_lbtguiders/dspcode/dsptiming/agw1g/tim3.asm
azcam_lbtguiders/dspcode/dsptiming/agw1g/tim3.lod
azcam_lbtguiders/dspcode/dsptiming/agw1g/tim3.ls
azcam_lbtguiders/dspcode/dsptiming/agw1g/tim3_boot.asm
azcam_lbtguiders/dspcode/dsptiming/agw1g/tim3_hdr.asm
azcam_lbtguiders/dspcode/dsptiming/agw1g/tim3_host.bat
azcam_lbtguiders/dspcode/dsptiming/agw1g/tim3_misc.asm
azcam_lbtguiders/dspcode/dsptiming/agw1g/tim3_rdccd.asm
azcam_lbtguiders/dspcode/dsptiming/agw1g/waveforms.asm
azcam_lbtguiders/dspcode/dsptiming/agw1g/ypars.asm
azcam_lbtguiders/dspcode/dsptiming/agw1w/dacs.asm
azcam_lbtguiders/dspcode/dsptiming/agw1w/int_noise.asm
azcam_lbtguiders/dspcode/dsptiming/agw1w/int_signal.asm
azcam_lbtguiders/dspcode/dsptiming/agw1w/p_3123_mpp.asm
azcam_lbtguiders/dspcode/dsptiming/agw1w/pq_3123_mpp.asm
azcam_lbtguiders/dspcode/dsptiming/agw1w/s_12_123n.asm
azcam_lbtguiders/dspcode/dsptiming/agw1w/switchstates.asm
azcam_lbtguiders/dspcode/dsptiming/agw1w/tim3.asm
azcam_lbtguiders/dspcode/dsptiming/agw1w/tim3.lod
azcam_lbtguiders/dspcode/dsptiming/agw1w/tim3.ls
azcam_lbtguiders-24.1.3.dist-info/LICENSE
azcam_lbtguiders-24.1.3.dist-info/WHEEL
azcam_lbtguiders-24.1.3.dist-info/METADATA
azcam_lbtguiders-24.1.3.dist-info/RECORD
