Metadata-Version: 2.1
Name: azcam-lbtguiders
Version: 24.1.3
Summary: Azcam extension for LBTO lbtguiders cameras
Keywords: ccd,imaging,astronomy,sensors
Author: Michael Lesser
Author-email: mlesser@arizona.edu
Requires-Python: >=3.10
Requires-Dist: azcam
Project-URL: Documentation, https://azcam.readthedocs.io/
Project-URL: Repository, https://github.com/mplesser/azcam-lbtguiders/
